{"deduplicationId":"84b23f0f-bf97-4333-8b5c-97746ebde620","time":"2023-10-01T03:19:04.606189+00:00","deviceInfo":{"tenantId":"52f14cd4-c6f1-4fbd-8f87-4025e1d49242","tenantName":"A Bit Byte","applicationId":"c47773da-3624-488a-9f37-545307ac7c28","applicationName":"To-Exporter","deviceProfileId":"ddffd76e-4d29-4121-96d3-99b3b9394e20","deviceProfileName":"LDS02","deviceName":"LDS-02","devEui":"a84041093187f23c","deviceClassEnabled":"CLASS_A","tags":{}},"devAddr":"00347b9d","adr":true,"dr":5,"fCnt":11,"fPort":10,"confirmed":false,"data":"DAwBAAAFAAAAAA==","object":{"LAST_DOOR_OPEN_DURATION":0.0,"ALARM":0.0,"DOOR_OPEN_TIMES":5.0,"BAT_V":3.084,"MOD":1.0,"DOOR_OPEN_STATUS":0.0},"rxInfo":[{"gatewayId":"24e124fffef7e872","uplinkId":53788,"time":"2023-10-01T03:19:04.606189+00:00","rssi":-56,"snr":14.2,"location":{"latitude":1.4437033714156848,"longitude":103.80742119859127},"context":"EcB6hw==","metadata":{"region_config_id":"as923","region_common_name":"AS923"},"crcStatus":"CRC_OK"}],"txInfo":{"frequency":923200000,"modulation":{"lora":{"bandwidth":125000,"spreadingFactor":7,"codeRate":"CR_4_5"}}}}